huobi/__init__.py
huobi/client/__init__.py
huobi/client/account.py
huobi/client/algo.py
huobi/client/etf.py
huobi/client/generic.py
huobi/client/margin.py
huobi/client/market.py
huobi/client/subuser.py
huobi/client/trade.py
huobi/client/wallet.py
huobi/connection/__init__.py
huobi/connection/restapi_sync_client.py
huobi/connection/subscribe_client.py
huobi/connection/websocket_req_client.py
huobi/connection/impl/__init__.py
huobi/connection/impl/private_def.py
huobi/connection/impl/restapi_invoker.py
huobi/connection/impl/restapi_request.py
huobi/connection/impl/websocket_manage.py
huobi/connection/impl/websocket_request.py
huobi/connection/impl/websocket_watchdog.py
huobi/constant/__init__.py
huobi/constant/definition.py
huobi/constant/result.py
huobi/constant/system.py
huobi/constant/test.py
huobi/exception/__init__.py
huobi/exception/huobi_api_exception.py
huobi/model/__init__.py
huobi/model/account/__init__.py
huobi/model/account/account.py
huobi/model/account/account_asset_valuation.py
huobi/model/account/account_balance.py
huobi/model/account/account_balance_req.py
huobi/model/account/account_history.py
huobi/model/account/account_ledger.py
huobi/model/account/account_point_group.py
huobi/model/account/account_point_result.py
huobi/model/account/account_point_transfer_result.py
huobi/model/account/account_transfer_result.py
huobi/model/account/account_update.py
huobi/model/account/account_update_event.py
huobi/model/account/balance.py
huobi/model/account/complete_subaccount.py
huobi/model/account/margin_balance_detail.py
huobi/model/account/sub_uid_management.py
huobi/model/algo/__init__.py
huobi/model/algo/cancel_order_result.py
huobi/model/algo/order_history_item.py
huobi/model/algo/order_list_item.py
huobi/model/etf/__init__.py
huobi/model/etf/etf_swap_config.py
huobi/model/etf/etf_swap_in_out.py
huobi/model/etf/etf_swap_list.py
huobi/model/etf/unitprice.py
huobi/model/generic/__init__.py
huobi/model/generic/chain.py
huobi/model/generic/exchange_info.py
huobi_client_sdk-2.2.1.dist-info/LICENSE
huobi_client_sdk-2.2.1.dist-info/METADATA
huobi_client_sdk-2.2.1.dist-info/WHEEL
huobi_client_sdk-2.2.1.dist-info/top_level.txt
huobi_client_sdk-2.2.1.dist-info/RECORD
